pylabinstrument/__init__.py
pylabinstrument/locateDll.py
pylabinstrument/ctools/__init__.py
pylabinstrument/ctools/_visa_enum.py
pylabinstrument/ctools/tools.py
pylabinstrument/ids/IDS.py
pylabinstrument/ids/__init__.py
pylabinstrument/ids/tools/__init__.py
pylabinstrument/ids/tools/_enum.py
pylabinstrument/ids/tools/_ids_wrapper.py
pylabinstrument/thorlabs/__init__.py
pylabinstrument/thorlabs/motion/DeviceManager.py
pylabinstrument/thorlabs/motion/KCubeDCServo.py
pylabinstrument/thorlabs/motion/KCubeSolenoid.py
pylabinstrument/thorlabs/motion/__init__.py
pylabinstrument/thorlabs/motion/tools/_KCubeDCServo.py
pylabinstrument/thorlabs/motion/tools/_KCubeDCServo_2.py
pylabinstrument/thorlabs/motion/tools/_KCubeSolenoid.py
pylabinstrument/thorlabs/motion/tools/__init__.py
pylabinstrument/thorlabs/motion/tools/_enumeration.py
pylabinstrument/thorlabs/motion/tools/_motor.py
pylabinstrument/thorlabs/motion/tools/_supported_devices.py
pylabinstrument/thorlabs/powermeter/DeviceManager.py
pylabinstrument/thorlabs/powermeter/PMSeries.py
pylabinstrument/thorlabs/powermeter/__init__.py
pylabinstrument/thorlabs/powermeter/tools/_TLPM_wrapper.py
pylabinstrument/thorlabs/powermeter/tools/__init__.py
pylabinstrument/thorlabs/spectrometer/CCS.py
pylabinstrument/thorlabs/spectrometer/__init__.py
pylabinstrument/thorlabs/spectrometer/tools/_TLCCS_wrapper.py
pylabinstrument/thorlabs/spectrometer/tools/__init__.py
pylabinstrument/thorlabs/templates/VisaObject.py
pylabinstrument/thorlabs/templates/__init__.py
pylabinstrument/thorlabs/thorlabs_examples/__init__.py
pylabinstrument/thorlabs/thorlabs_examples/example_01_general_procedure.py
pylabinstrument-1.0.303.dist-info/METADATA
pylabinstrument-1.0.303.dist-info/RECORD
pylabinstrument-1.0.303.dist-info/WHEEL
pylabinstrument-1.0.303.dist-info/top_level.txt
