Metadata-Version: 2.1
Name: pylabinstrument
Version: 1.0.303
Summary: tools to control equipment such as motors, power meters, camera, etc
Home-page: https://github.com/psklight/pylabinstrument
Author: Pisek Kultavewuti
Author-email: psk.light@gmail.com
License: UNKNOWN
Platform: UNKNOWN
Classifier: Programming Language :: Python :: 3
Classifier: License :: OSI Approved :: MIT License
Classifier: Operating System :: Microsoft :: Windows
Requires-Dist: numpy
Requires-Dist: pandas
Requires-Dist: pyueye
Requires-Dist: pyvisa
